PyBeacon/PyBeacon.py
PyBeacon/__init__.py
PyBeacon-0.3.0.0.dist-info/DESCRIPTION.rst
PyBeacon-0.3.0.0.dist-info/METADATA
PyBeacon-0.3.0.0.dist-info/RECORD
PyBeacon-0.3.0.0.dist-info/WHEEL
PyBeacon-0.3.0.0.dist-info/entry_points.txt
PyBeacon-0.3.0.0.dist-info/metadata.json
PyBeacon-0.3.0.0.dist-info/top_level.txt
